ghostr/__init__.py
ghostr/helpers.py
ghostr-0.1.2.dist-info/LICENCE
ghostr-0.1.2.dist-info/METADATA
ghostr-0.1.2.dist-info/WHEEL
ghostr-0.1.2.dist-info/top_level.txt
ghostr-0.1.2.dist-info/RECORD
