Metadata-Version: 2.1
Name: ghostr
Version: 0.1.2
Summary: Strings that ignore part of themselves.
Home-page: https://github.com/Exahilosys/ghostr
License: MIT
Platform: UNKNOWN
Provides-Extra: docs
Requires-Dist: sphinx ; extra == 'docs'
Requires-Dist: sphinx-rtd-theme ; extra == 'docs'
